setup.py
data_load_script/__init__.py
data_load_script/business_logic.py
data_load_script/data_integration.py
data_load_script/input_data_handle.py
data_load_script/input_verification.py
data_load_script/item_upc_generator.py
data_load_script/main_application.py
data_load_script/output_data_handle.py
data_load_script/patch_cer_number.py
data_load_script/patch_format.py
data_load_script/patch_remove_duplicates.py
data_load_script.egg-info/PKG-INFO
data_load_script.egg-info/SOURCES.txt
data_load_script.egg-info/dependency_links.txt
data_load_script.egg-info/not-zip-safe
data_load_script.egg-info/top_level.txt