Metadata-Version: 1.0
Name: data-load-script
Version: 1.5
Summary: load the input data from Amazon S3, generate main tables and BOM tables, and upload to Amazon S3
Home-page: http://github.com/ghao2
Author: haoguoxuan
Author-email: haoguoxuan@gmail.com
License: MIT
Platform: UNKNOWN
